Workbook

Sheet PRESUPUESTO
A6: Cargar sólo las celdas blancas. No cargar las celdas coloreadas ya que contienen fórmulas
A8: CONCEPTO | B8: Periodo 1 | C8: Periodo 2 | D8: Periodo 3 | E8: Periodo 4 | F8: Periodo 5 | G8: Periodo 6 | H8: Periodo 7 | I8: Periodo 8 | J8: Periodo 9 | K8: Periodo 10 | L8: Periodo 11 | M8: Periodo 12 | N8: Periodo 13 | O8: Periodo 14 | P8: Periodo 15 | Q8: Periodo 16 | R8: Periodo 17 | S8: Periodo 18 | T8: Periodo 19 | U8: Periodo 20 | V8: Periodo 21 | W8: Periodo 22 | X8: Periodo 23 | Y8: Periodo 24 | Z8: TOTAL
A9: Dev 1 · ipacheco · 6 h/sem × 10 USD/h | B9: 60 | C9: 60 | D9: 60 | E9: 60 | F9: 60 | G9: 60 | H9: 60 | I9: 60 | J9: 60 | K9: 60 | L9: 60 | M9: 60 | N9: 60 | Z9: =SUM(B9:Y9)
A10: Dev 2 · jrudolph · 6 h/sem × 10 USD/h | B10: 60 | C10: 60 | D10: 60 | E10: 60 | F10: 60 | G10: 60 | H10: 60 | I10: 60 | J10: 60 | K10: 60 | L10: 60 | M10: 60 | N10: 60 | Z10: =SUM(B10:Y10) -> 720
A11: Dev 3 · jfsiaba · 6 h/sem × 10 USD/h | B11: 60 | C11: 60 | D11: 60 | E11: 60 | F11: 60 | G11: 60 | H11: 60 | I11: 60 | J11: 60 | K11: 60 | L11: 60 | M11: 60 | N11: 60 | Z11: =SUM(B11:Y11) -> 720
A12: Infra · Azure B1 (back) · 13,14 USD/mes | E12: 13.14 | I12: 13.14 | M12: 13.14 | Z12: =SUM(B12:Y12) -> 39.42
A13: Infra · Vercel + Neon (plan gratis) | Z13: =SUM(B13:Y13) -> 0
A14: IA · Claude Code/ChatGPT · 3 × 20 USD/mes | B14: 60 | F14: 60 | K14: 60 | Z14: =SUM(B14:Y14) -> 180
Z15: =SUM(B15:Y15) -> 0
Z16: =SUM(B16:Y16) -> 0
Z17: =SUM(B17:Y17) -> 0
Z18: =SUM(B18:Y18) -> 0
Z19: =SUM(B19:Y19) -> 0
Z20: =SUM(B20:Y20) -> 0
Z21: =SUM(B21:Y21) -> 0
Z22: =SUM(B22:Y22) -> 0
Z23: =SUM(B23:Y23) -> 0
Z24: =SUM(B24:Y24) -> 0
Z25: =SUM(B25:Y25) -> 0
Z26: =SUM(B26:Y26) -> 0
... Z33: =SUM(B33:Y33) -> 0
A34: TOTAL por periodo | B34: =SUM(B9:B33) | C34: =SUM(C9:C33) -> 180 | D34: =SUM(D9:D33) -> 180 | E34: =SUM(E9:E33) -> 193.14 | F34: =SUM(F9:F33) -> 240 | G34: =SUM(G9:G33) -> 180 | H34: =SUM(H9:H33) -> 180 | I34: =SUM(I9:I33) -> 193.14 | ... Z34: =SUM(Z9:Z33) -> 2379.42
A35: TOTAL acumulado | B35: =B34 -> 240 | C35: =B35+C34 -> 420 | D35: =C35+D34 | E35: =D35+E34 -> 793.14 | F35: =E35+F34 -> 1033.14 | G35: =F35+G34 -> 1213.14 | H35: =G35+H34 | I35: =H35+I34 | J35: =I35+J34 | ... Y35: =X35+Y34 -> 2559.42
A38: VALOR PLANEADO (PV)  | B38: =B34 -> 240 | C38: =C34 | D38: =D34 -> 180 | E38: =E34 -> 193.14 | F38: =F34 -> 240 | G38: =G34 -> 180 | H38: =H34 | I38: =I34 -> 193.14 | ... Y38: =Y34 -> 0 | Z38: Presup. al cierre (BAC)
A39: VALOR PLANEADO (PV)  | B39: =B38 -> 240 | C39: =C38 | D39: =D38 -> 180 | E39: =E38 -> 193.14 | F39: =F38 -> 240 | G39: =G38 -> 180 | H39: =H38 -> 180 | I39: =I38 -> 193.14 | ... Y39: =Y38 -> 0 | Z39: =Z34 -> 2559.42
A40: Valor Planeado acumulado | B40: =B35 -> 240 | C40: =C35 | D40: =D35 -> 600 | E40: =E35 -> 793.14 | F40: =F35 -> 1033.14 | G40: =G35 -> 1213.14 | H40: =H35 | I40: =I35 -> 1586.28 | ... Y40: =Y35 -> 2379.42
A41: VALOR GANADO (EV)  | B41: ='Avance semanal'!J6 -> 63.517778 | C41: ='Avance semanal'!J7 -> 377.75755 | D41: ='Avance semanal'!J8 -> 100.70455 | E41: ='Avance semanal'!J9 -> 349.92521 | F41: ='Avance semanal'!J10 -> 303.61498 | G41: ='Avance semanal'!J11 -> 214.22814
A42: Valor Ganado acumulado | B42: =IF(B41=0,NA(),B41) -> 63.517778 | C42: =IF(C41=0,NA(),B42+C41) -> 441.27533 | D42: =IF(D41=0,NA(),C42+D41) | E42: =IF(E41=0,NA(),D42+E41) -> 863.14 | F42: =IF(F41=0,NA(),E42+F41) -> 1133.14 | G42: =IF(G41=0,NA(),F42+G41) -> 1363.14 | H42: =IF(H41=0,NA(),G42+H41) -> #N/A | I42: =IF(I41=0,NA(),H42+I41) -> #N/A | J42: =IF(J41=0,NA(),I42+J41) -> #N/A | ... Y42: =IF(Y41=0,NA(),X42+Y41) -> #N/A
A43: COSTO REAL (AC)  | B43: ='Avance semanal'!K6 -> 240 | C43: ='Avance semanal'!K7 -> 180 | D43: ='Avance semanal'!K8 -> 180 | E43: ='Avance semanal'!K9 -> 193.14 | F43: ='Avance semanal'!K10 -> 240 | G43: ='Avance semanal'!K11 -> 180
A44: Costo Real acumulado | B44: =IF(B41=0,NA(),B43) -> 240 | C44: =IF(C41=0,NA(),B44+C43) -> 420 | D44: =IF(D41=0,NA(),C44+D43) | E44: =IF(E41=0,NA(),D44+E43) -> 793.14 | F44: =IF(F41=0,NA(),E44+F43) -> 1033.14 | G44: =IF(G41=0,NA(),F44+G43) -> 1213.14 | H44: =IF(H41=0,NA(),G44+H43) -> #N/A | I44: =IF(I41=0,NA(),H44+I43) -> #N/A | J44: =IF(J41=0,NA(),I44+J43) -> #N/A | ... Y44: =IF(Y41=0,NA(),X44+Y43) -> #N/A
A45: SPI | B45: =IFERROR(B42/B40,"-") | C45: =IFERROR(C42/C40,"-") -> 1.047619 | D45: =IFERROR(D42/D40,"-") -> 1.0666667 | E45: =IFERROR(E42/E40,"-") -> 1.0882568 | F45: =IFERROR(F42/F40,"-") -> 1.0967923 | G45: =IFERROR(G42/G40,"-") -> 1.1236461 | H45: =IFERROR(H42/H40,"-") -> - | I45: =IFERROR(I42/I40,"-") -> - | ... Y45: =IFERROR(Y42/Y40,"-") -> -
A46: CPI | B46: =IFERROR(B42/B44,"-") -> 0.26465741 | C46: =IFERROR(C42/C44,"-") | D46: =IFERROR(D42/D44,"-") -> 1.0666667 | E46: =IFERROR(E42/E44,"-") -> 1.0882568 | F46: =IFERROR(F42/F44,"-") -> 1.0967923 | G46: =IFERROR(G42/G44,"-") -> 1.1236461 | H46: =IFERROR(H42/H44,"-") -> - | I46: =IFERROR(I42/I44,"-") -> - | ... Y46: =IFERROR(Y42/Y44,"-") -> -

Sheet Curva S
A1: SportMatch — Valor Ganado (EVM) y Curva S
A2: Equipo 11 · Corte 17/09/2026 (semana 6, cierre del S1) · USD acumulados (devs + infra + IA) · Base: WBS y Cronograma v4 · Datos desde PRESUPUESTO y Avance semanal
A4: Semana | B4: Cierre (jueves) | C4: Hito | D4: PV acumulado (USD) | E4: EV acumulado (USD) | F4: AC acumulado (USD) | G4: Horas plan acum. | H4: Horas ganadas acum. | I4: Horas reales acum. | K4: Parámetros
A5: 1 | B5: 13/08 | C5: S1 · Capacitación | D5: =PRESUPUESTO!B40 -> 240 | E5: =IFERROR(PRESUPUESTO!B42,"") -> 63.517778 | F5: =IFERROR(PRESUPUESTO!B44,"") -> 240 | G5: =SUM('Avance semanal'!$D$6:D6) -> 18 | H5: =SUM('Avance semanal'!$F$6:F6) -> 5.5 | I5: =SUM('Avance semanal'!$E$6:E6) -> 18 | K5: Semana de corte | L5: 6
A6: 2 | B6: 20/08 | C6: S1 | D6: =PRESUPUESTO!C40 -> 420 | E6: =IFERROR(PRESUPUESTO!C42,"") -> 441.27533 | F6: =IFERROR(PRESUPUESTO!C44,"") -> 420 | G6: =SUM('Avance semanal'!$D$6:D7) -> 36 | H6: =SUM('Avance semanal'!$F$6:F7) -> 38.21 | I6: =SUM('Avance semanal'!$E$6:E7) -> 36 | K6: Tarifa desarrollo (USD/h) | L6: 10
A7: 3 | B7: 27/08 | C7: S1 | D7: =PRESUPUESTO!D40 -> 600 | E7: =IFERROR(PRESUPUESTO!D42,"") -> 541.97988 | F7: =IFERROR(PRESUPUESTO!D44,"") -> 600 | G7: =SUM('Avance semanal'!$D$6:D8) -> 54 | H7: =SUM('Avance semanal'!$F$6:F8) -> 46.93 | I7: =SUM('Avance semanal'!$E$6:E8) -> 54 | K7: BAC total del proyecto (USD) | L7: 8063.3
A8: 4 | B8: 03/09 | C8: S1 | D8: =PRESUPUESTO!E40 -> 793.14 | E8: =IFERROR(PRESUPUESTO!E42,"") -> 891.90509 | F8: =IFERROR(PRESUPUESTO!E44,"") -> 793.14 | G8: =SUM('Avance semanal'!$D$6:D9) -> 72 | H8: =SUM('Avance semanal'!$F$6:F9) -> 77.23 | I8: =SUM('Avance semanal'!$E$6:E9) -> 72 | K8: BAC línea base EVM (devs + infra + IA) | L8: =PRESUPUESTO!Z39 -> 2559.42
A9: 5 | B9: 10/09 | C9: S1 | D9: =PRESUPUESTO!F40 -> 1033.14 | E9: =IFERROR(PRESUPUESTO!F42,"") -> 1195.5201 | F9: =IFERROR(PRESUPUESTO!F44,"") -> 1033.14 | G9: =SUM('Avance semanal'!$D$6:D10) -> 90 | H9: =SUM('Avance semanal'!$F$6:F10) -> 103.52 | I9: =SUM('Avance semanal'!$E$6:E10) -> 90 | K9: Esfuerzo de desarrollo (h, Cronograma v4) | L9: 221.62
A10: 6 | B10: 17/09 | C10: S1 · CORTE (steering 1) | D10: =PRESUPUESTO!G40 -> 1213.14 | E10: =IFERROR(PRESUPUESTO!G42,"") -> 1409.7482 | F10: =IFERROR(PRESUPUESTO!G44,"") -> 1213.14 | G10: =SUM('Avance semanal'!$D$6:D11) -> 108 | H10: =SUM('Avance semanal'!$F$6:F11) -> 122.07 | I10: =SUM('Avance semanal'!$E$6:E11) -> 108 | K10: Métrica al corte | L10: USD | M10: Horas | N10: Lectura
A11: 7 | B11: 24/09 | C11: S2 | D11: =PRESUPUESTO!H40 -> 1393.14 | E11: =IFERROR(PRESUPUESTO!H42,"") | F11: =IFERROR(PRESUPUESTO!H44,"") | G11: =SUM('Avance semanal'!$D$6:D12) -> 126 | K11: PV — Valor Planeado | L11: =INDEX(PRESUPUESTO!$B$40:$Y$40,$L$5) -> 1213.14 | M11: =INDEX($G$5:$G$17,$L$5) -> 108
A12: 8 | B12: 01/10 | C12: S2 | D12: =PRESUPUESTO!I40 -> 1586.28 | E12: =IFERROR(PRESUPUESTO!I42,"") | F12: =IFERROR(PRESUPUESTO!I44,"") | G12: =SUM('Avance semanal'!$D$6:D13) -> 144 | K12: EV — Valor Ganado | L12: =INDEX(PRESUPUESTO!$B$42:$Y$42,$L$5) -> 1409.7482 | M12: =INDEX($H$5:$H$17,$L$5) -> 122.07
A13: 9 | B13: 08/10 | C13: S2 | D13: =PRESUPUESTO!J40 -> 1766.28 | E13: =IFERROR(PRESUPUESTO!J42,"") | F13: =IFERROR(PRESUPUESTO!J44,"") | G13: =SUM('Avance semanal'!$D$6:D14) -> 162 | K13: AC — Costo Real | L13: =INDEX(PRESUPUESTO!$B$44:$Y$44,$L$5) -> 1213.14 | M13: =INDEX($I$5:$I$17,$L$5) -> 108
A14: 10 | B14: 15/10 | C14: S2 · MVP | D14: =PRESUPUESTO!K40 -> 2006.28 | E14: =IFERROR(PRESUPUESTO!K42,"") | F14: =IFERROR(PRESUPUESTO!K44,"") | G14: =SUM('Avance semanal'!$D$6:D15) -> 180 | K14: CV = EV − AC | L14: =L12-L13 -> 196.60821 | M14: =M12-M13 -> 14.07 | N14: =IF(L14>=0,"Bajo presupuesto","Sobre presupuesto") -> Bajo presupuesto
A15: 11 | B15: 22/10 | C15: S3 | D15: =PRESUPUESTO!L40 -> 2186.28 | E15: =IFERROR(PRESUPUESTO!L42,"") | F15: =IFERROR(PRESUPUESTO!L44,"") | G15: =SUM('Avance semanal'!$D$6:D16) -> 198 | K15: SV = EV − PV | L15: =L12-L11 -> 196.60821 | M15: =M12-M11 -> 14.07 | N15: =IF(L15>=0,"Adelantado al plan","Atrasado") -> Adelantado al plan
A16: 12 | B16: 29/10 | C16: S3 | D16: =PRESUPUESTO!M40 -> 2379.42 | E16: =IFERROR(PRESUPUESTO!M42,"") | F16: =IFERROR(PRESUPUESTO!M44,"") | G16: =SUM('Avance semanal'!$D$6:D17) -> 216 | K16: CPI = EV / AC | L16: =L12/L13 -> 1.1620656 | N16: =IF(L16>=1,"Eficiente en costo (>1)","Ineficiente (<1)") -> Eficiente en costo (>1)
A17: 13 | B17: 05/11 | C17: S3 · Fin del desarrollo | D17: =PRESUPUESTO!N40 -> 2559.42 | E17: =IFERROR(PRESUPUESTO!N42,"") | F17: =IFERROR(PRESUPUESTO!N44,"") | G17: =SUM('Avance semanal'!$D$6:D18) -> 234 | K17: SPI = EV / PV | L17: =L12/L11 -> 1.1620656 | N17: =IF(L17>=1,"Por encima del ritmo (>1)","Por debajo del ritmo (<1)") -> Por encima del ritmo (>1)
A18: Gráfico: Curva S — PV vs EV vs AC | K18: EAC = BAC EVM / CPI | L18: =L8/L16 -> 2202.4747 | N18: Costo estimado al cierre
K19: ETC = EAC − AC | L19: =L18-L13 -> 989.3347 | N19: Costo para completar
K20: VAC = BAC EVM − EAC | L20: =L8-L18 -> 356.9453 | N20: =IF(L20>=0,"Ahorro proyectado","Sobrecosto proyectado") -> Ahorro proyectado
K23: Notas y supuestos
K24: • PV: 3 filas de devs (6 h/sem × 10 USD/h = 60 USD/sem c/u) durante 13 semanas + Azure B1 desde el deploy (29/08) + Claude Code/ChatGPT (3 × 20 USD/mes). La semana de reserva (05/11 → 12/11) es reserva de gestión y no entra.
K25: • Vercel (Hobby) y Neon (Free) no tienen costo. Firebase Auth, GitHub Actions y GHCR tampoco.
K26: • EV = % completo × BAC EVM. % completo = horas estimadas de los paquetes de la WBS cerrados / 221,62 h de desarrollo. Semanal: 5,5 · 32,71 · 8,72 · 30,3 · 26,29 · 18,55 h (122,07 h).
K27: • AC: 18 h reales por semana (108 h) + lo facturado de infra e IA. El detalle está en la hoja Avance semanal.
K28: • EAC, ETC y VAC usan el BAC de la línea base EVM (L8), la misma base que PV, EV y AC. BAC total del proyecto: 442 HH + infra e IA + 20 % de contingencia = 8.063,30 USD, sin CAPEX.
K29: • La curva no incluye las 16 h/sem de management (20 USD/h).
K30: • Los N/A de PRESUPUESTO (semanas 7 a 24) vienen de la plantilla y cortan las curvas EV y AC en la semana de corte.
K31: • En el gráfico, EV y AC toman PRESUPUESTO!B:G (semanas 1 a 6). Al cargar semanas nuevas, extender el rango de esas dos series.
K32: • Celdas amarillas con texto azul = datos a editar. Texto verde = vínculo a otra hoja.

Sheet Avance semanal
A1: SportMatch — Avance semanal (horas y valor ganado)
A2: Equipo 11 · Semanas de jueves a jueves (06/08 → 05/11) · S1 = sem 1–6, S2 = 7–10, S3 = 11–13 · Reserva 05/11 → 12/11 fuera del BAC · Celdas amarillas = datos a editar
A5: Semana | B5: Cierre | C5: Hito | D5: Horas plan | E5: Horas reales | F5: Horas ganadas | G5: % completo de la semana | H5: Infra + IA plan (USD) | I5: Infra + IA real (USD) | J5: EV total (USD) = % × BAC EVM | K5: AC total (USD) | L5: Qué pasó en la semana
A6: 1 | B6: 13/08 | C6: S1 · Capacitación | D6: =(PRESUPUESTO!B9+PRESUPUESTO!B10+PRESUPUESTO!B11)/'Curva S'!$L$6 -> 18 | E6: 18 | F6: 5.5 | G6: =F6/'Curva S'!$L$9 -> 0.024817255 | H6: =PRESUPUESTO!B12+PRESUPUESTO!B13+PRESUPUESTO!B14 -> 60 | I6: =H6 -> 60 | J6: =G6*'Curva S'!$L$8 -> 63.517778 | K6: =E6*'Curva S'!$L$6+I6 -> 240 | L6: Cierran 3.1.1, 3.1.3
A7: 2 | B7: 20/08 | C7: S1 | D7: =(PRESUPUESTO!C9+PRESUPUESTO!C10+PRESUPUESTO!C11)/'Curva S'!$L$6 -> 18 | E7: 18 | F7: 32.71 | G7: =F7/'Curva S'!$L$9 -> 0.14759498 | H7: =PRESUPUESTO!C12+PRESUPUESTO!C13+PRESUPUESTO!C14 -> 0 | I7: =H7 -> 0 | J7: =G7*'Curva S'!$L$8 -> 377.75755 | K7: =E7*'Curva S'!$L$6+I7 -> 180 | L7: Cierran 3.1.2, 3.2.1, 4.1.1, 4.1.3, 4.1.4, 4.2.1, 4.2.2, 4.2.3, 10.2.1
A8: 3 | B8: 27/08 | C8: S1 | D8: =(PRESUPUESTO!D9+PRESUPUESTO!D10+PRESUPUESTO!D11)/'Curva S'!$L$6 -> 18 | E8: 18 | F8: 8.72 | G8: =F8/'Curva S'!$L$9 -> 0.039346629 | H8: =PRESUPUESTO!D12+PRESUPUESTO!D13+PRESUPUESTO!D14 -> 0 | I8: =H8 -> 0 | J8: =G8*'Curva S'!$L$8 -> 100.70455 | K8: =E8*'Curva S'!$L$6+I8 -> 180 | L8: Cierran 3.2.2, 4.1.2, 6.1.1, 9.1.4
A9: 4 | B9: 03/09 | C9: S1 | D9: =(PRESUPUESTO!E9+PRESUPUESTO!E10+PRESUPUESTO!E11)/'Curva S'!$L$6 -> 18 | E9: 18 | F9: 30.3 | G9: =F9/'Curva S'!$L$9 -> 0.13672051 | H9: =PRESUPUESTO!E12+PRESUPUESTO!E13+PRESUPUESTO!E14 -> 13.14 | I9: =H9 -> 13.14 | J9: =G9*'Curva S'!$L$8 -> 349.92521 | K9: =E9*'Curva S'!$L$6+I9 -> 193.14 | L9: Cierran 3.2.3, 4.2.5, 6.1.2, 6.1.5, 6.2.3, 6.3.5, 7.2.1, 9.1.1, 9.1.2, 9.1.3
A10: 5 | B10: 10/09 | C10: S1 | D10: =(PRESUPUESTO!F9+PRESUPUESTO!F10+PRESUPUESTO!F11)/'Curva S'!$L$6 -> 18 | E10: 18 | F10: 26.29 | G10: =F10/'Curva S'!$L$9 -> 0.11862648 | H10: =PRESUPUESTO!F12+PRESUPUESTO!F13+PRESUPUESTO!F14 -> 60 | I10: =H10 -> 60 | J10: =G10*'Curva S'!$L$8 -> 303.61498 | K10: =E10*'Curva S'!$L$6+I10 -> 240 | L10: Cierran 5.1.2, 5.2.1, 6.1.3, 6.2.1, 6.2.4, 6.3.1, 6.3.2, 6.3.3, 7.2.2
A11: 6 | B11: 17/09 | C11: S1 · CORTE (steering 1) | D11: =(PRESUPUESTO!G9+PRESUPUESTO!G10+PRESUPUESTO!G11)/'Curva S'!$L$6 -> 18 | E11: 18 | F11: 18.55 | G11: =F11/'Curva S'!$L$9 -> 0.083701832 | H11: =PRESUPUESTO!G12+PRESUPUESTO!G13+PRESUPUESTO!G14 -> 0 | I11: =H11 -> 0 | J11: =G11*'Curva S'!$L$8 -> 214.22814 | K11: =E11*'Curva S'!$L$6+I11 -> 180 | L11: Cierran 4.2.4, 5.1.3, 5.1.5, 5.2.4, 5.2.5, 6.2.2, 6.3.4, 6.4.1
A12: 7 | B12: 24/09 | C12: S2 | D12: =(PRESUPUESTO!H9+PRESUPUESTO!H10+PRESUPUESTO!H11)/'Curva S'!$L$6 -> 18 | H12: =PRESUPUESTO!H12+PRESUPUESTO!H13+PRESUPUESTO!H14 -> 0 | L12: Pendiente (línea base)
A13: 8 | B13: 01/10 | C13: S2 | D13: =(PRESUPUESTO!I9+PRESUPUESTO!I10+PRESUPUESTO!I11)/'Curva S'!$L$6 -> 18 | H13: =PRESUPUESTO!I12+PRESUPUESTO!I13+PRESUPUESTO!I14 -> 13.14 | L13: Pendiente (línea base)
A14: 9 | B14: 08/10 | C14: S2 | D14: =(PRESUPUESTO!J9+PRESUPUESTO!J10+PRESUPUESTO!J11)/'Curva S'!$L$6 -> 18 | H14: =PRESUPUESTO!J12+PRESUPUESTO!J13+PRESUPUESTO!J14 -> 0 | L14: Pendiente (línea base)
A15: 10 | B15: 15/10 | C15: S2 · MVP | D15: =(PRESUPUESTO!K9+PRESUPUESTO!K10+PRESUPUESTO!K11)/'Curva S'!$L$6 -> 18 | H15: =PRESUPUESTO!K12+PRESUPUESTO!K13+PRESUPUESTO!K14 -> 60 | L15: Pendiente (línea base)
A16: 11 | B16: 22/10 | C16: S3 | D16: =(PRESUPUESTO!L9+PRESUPUESTO!L10+PRESUPUESTO!L11)/'Curva S'!$L$6 -> 18 | H16: =PRESUPUESTO!L12+PRESUPUESTO!L13+PRESUPUESTO!L14 -> 0 | L16: Pendiente (línea base)
A17: 12 | B17: 29/10 | C17: S3 | D17: =(PRESUPUESTO!M9+PRESUPUESTO!M10+PRESUPUESTO!M11)/'Curva S'!$L$6 -> 18 | H17: =PRESUPUESTO!M12+PRESUPUESTO!M13+PRESUPUESTO!M14 -> 13.14 | L17: Pendiente (línea base)
A18: 13 | B18: 05/11 | C18: S3 · Fin del desarrollo | D18: =(PRESUPUESTO!N9+PRESUPUESTO!N10+PRESUPUESTO!N11)/'Curva S'!$L$6 -> 18 | H18: =PRESUPUESTO!N12+PRESUPUESTO!N13+PRESUPUESTO!N14 -> 0 | L18: Pendiente (línea base)
A19: Total al corte | D19: =SUM(D6:D11) -> 108 | E19: =SUM(E6:E11) -> 108 | F19: =SUM(F6:F11) -> 122.07 | G19: =SUM(G6:G11) -> 0.55080769 | H19: =SUM(H6:H11) -> 133.14 | I19: =SUM(I6:I11) -> 133.14 | J19: =SUM(J6:J11) -> 1409.7482 | K19: =SUM(K6:K11) -> 1213.14 | L19: Semanas 1 a 6
A20: Cómo leer esta hoja
A21: • Horas plan: 3 devs × 6 h/sem, sale de las filas de devs de PRESUPUESTO. Horas reales: lo cargado por el equipo (18 h/sem).
A22: • Horas ganadas: horas estimadas (WBS v4) de los paquetes que cierran en la semana, según el Cronograma v4 §4. Total al corte: 122,07 h de 221,62 h de desarrollo. Los paquetes parciales no suman.
A23: • Infra + IA: Azure B1 (13,14 USD/mes) desde el deploy del 29/08 (SPO-175/176) y Claude Code/ChatGPT (3 × 20 USD/mes, se cobra el 10 de cada mes).
A24: • EV total = % completo de la semana × BAC EVM (Curva S!L8). AC total = horas reales × tarifa + Infra/IA facturados. Ambas columnas alimentan las filas 41 y 43 de PRESUPUESTO.

Sheet Ayuda
