Workbook

Sheet PRESUPUESTO
A6: Cargar sólo las celdas blancas. No cargar las celdas coloreadas ya que contienen fórmulas
A8: CONCEPTO | B8: Periodo 1 | C8: Periodo 2 | D8: Periodo 3 | E8: Periodo 4 | F8: Periodo 5 | G8: Periodo 6 | H8: Periodo 7 | I8: Periodo 8 | J8: Periodo 9 | K8: Periodo 10 | L8: Periodo 11 | M8: Periodo 12 | N8: Periodo 13 | O8: Periodo 14 | P8: Periodo 15 | Q8: Periodo 16 | R8: Periodo 17 | S8: Periodo 18 | T8: Periodo 19 | U8: Periodo 20 | V8: Periodo 21 | W8: Periodo 22 | X8: Periodo 23 | Y8: Periodo 24 | Z8: TOTAL
A9: Dev 1 · ipacheco · 6 h/sem × 10 USD/h | B9: 60 | C9: 60 | D9: 60 | E9: 60 | F9: 60 | G9: 60 | H9: 60 | I9: 60 | J9: 60 | K9: 60 | L9: 60 | M9: 60 | N9: 60 | Z9: =SUM(B9:Y9)
A10: Dev 2 · jrudolph · 6 h/sem × 10 USD/h | B10: 60 | C10: 60 | D10: 60 | E10: 60 | F10: 60 | G10: 60 | H10: 60 | I10: 60 | J10: 60 | K10: 60 | L10: 60 | M10: 60 | N10: 60 | Z10: =SUM(B10:Y10)
A11: Dev 3 · jfsiaba · 6 h/sem × 10 USD/h | B11: 60 | C11: 60 | D11: 60 | E11: 60 | F11: 60 | G11: 60 | H11: 60 | I11: 60 | J11: 60 | K11: 60 | L11: 60 | M11: 60 | N11: 60 | Z11: =SUM(B11:Y11)
A12: Infra · Azure B1 (back) · 13,14 USD/mes | E12: 13.14 | I12: 13.14 | M12: 13.14 | Z12: =SUM(B12:Y12)
A13: Infra · Vercel + Neon + Google Maps/Places (plan gratis) | Z13: =SUM(B13:Y13)
A14: IA · Claude Code/ChatGPT · 3 × 20 USD/mes | B14: 60 | F14: 60 | K14: 60 | Z14: =SUM(B14:Y14)
A15: Lead · PM · 4 h/sem × 20 USD/h | B15: 80 | C15: 80 | D15: 80 | E15: 80 | F15: 80 | G15: 80 | H15: 80 | I15: 80 | J15: 80 | K15: 80 | L15: 80 | M15: 80 | N15: 80 | Z15: =SUM(B15:Y15)
A16: Lead · PO · 4 h/sem × 20 USD/h | B16: 80 | C16: 80 | D16: 80 | E16: 80 | F16: 80 | G16: 80 | H16: 80 | I16: 80 | J16: 80 | K16: 80 | L16: 80 | M16: 80 | N16: 80 | Z16: =SUM(B16:Y16)
A17: Lead · Tech Lead · 4 h/sem × 20 USD/h | B17: 80 | C17: 80 | D17: 80 | E17: 80 | F17: 80 | G17: 80 | H17: 80 | I17: 80 | J17: 80 | K17: 80 | L17: 80 | M17: 80 | N17: 80 | Z17: =SUM(B17:Y17)
A18: Lead · QA Lead · 4 h/sem × 20 USD/h | B18: 80 | C18: 80 | D18: 80 | E18: 80 | F18: 80 | G18: 80 | H18: 80 | I18: 80 | J18: 80 | K18: 80 | L18: 80 | M18: 80 | N18: 80 | Z18: =SUM(B18:Y18)
A19: Contingencia de actividades · 10 % del costo de la semana (Curva S!L7, dentro del BAC) | B19: ='Curva S'!$L$7*SUM(B9:B18) | C19: ='Curva S'!$L$7*SUM(C9:C18) | D19: ='Curva S'!$L$7*SUM(D9:D18) | E19: ='Curva S'!$L$7*SUM(E9:E18) | F19: ='Curva S'!$L$7*SUM(F9:F18) | G19: ='Curva S'!$L$7*SUM(G9:G18) | H19: ='Curva S'!$L$7*SUM(H9:H18) | I19: ='Curva S'!$L$7*SUM(I9:I18) | ... N19: ='Curva S'!$L$7*SUM(N9:N18) | Z19: =SUM(B19:Y19)
Z20: =SUM(B20:Y20)
Z21: =SUM(B21:Y21)
Z22: =SUM(B22:Y22)
Z23: =SUM(B23:Y23)
Z24: =SUM(B24:Y24)
Z25: =SUM(B25:Y25)
Z26: =SUM(B26:Y26)
Z27: =SUM(B27:Y27)
Z28: =SUM(B28:Y28)
Z29: =SUM(B29:Y29)
Z30: =SUM(B30:Y30)
Z31: =SUM(B31:Y31)
... Z33: =SUM(B33:Y33)
A34: TOTAL por periodo | B34: =SUM(B9:B33) | C34: =SUM(C9:C33) | D34: =SUM(D9:D33) | E34: =SUM(E9:E33) | F34: =SUM(F9:F33) | G34: =SUM(G9:G33) | H34: =SUM(H9:H33) | I34: =SUM(I9:I33) | ... Z34: =SUM(Z9:Z33)
A35: TOTAL acumulado | B35: =B34 | C35: =B35+C34 | D35: =C35+D34 | E35: =D35+E34 | F35: =E35+F34 | G35: =F35+G34 | H35: =G35+H34 | I35: =H35+I34 | J35: =I35+J34 | ... Y35: =X35+Y34
A38: VALOR PLANEADO (PV)  | B38: =B34 | C38: =C34 | D38: =D34 | E38: =E34 | F38: =F34 | G38: =G34 | H38: =H34 | I38: =I34 | ... Y38: =Y34 | Z38: Presup. al cierre (BAC)
A39: VALOR PLANEADO (PV)  | B39: =B38 | C39: =C38 | D39: =D38 | E39: =E38 | F39: =F38 | G39: =G38 | H39: =H38 | I39: =I38 | ... Y39: =Y38 | Z39: =Z34
A40: Valor Planeado acumulado | B40: =B35 | C40: =C35 | D40: =D35 | E40: =E35 | F40: =F35 | G40: =G35 | H40: =H35 | I40: =I35 | ... Y40: =Y35
A41: VALOR GANADO (EV)  | B41: ='Avance semanal'!J6 | C41: ='Avance semanal'!J7 | D41: ='Avance semanal'!J8 | E41: ='Avance semanal'!J9 | F41: ='Avance semanal'!J10 | G41: ='Avance semanal'!J11 | H41: ='Avance semanal'!J12 | I41: ='Avance semanal'!J13 | J41: ='Avance semanal'!J14 | K41: ='Avance semanal'!J15
A42: Valor Ganado acumulado | B42: =IF(B41=0,NA(),B41) | C42: =IF(C41=0,NA(),B42+C41) | D42: =IF(D41=0,NA(),C42+D41) | E42: =IF(E41=0,NA(),D42+E41) | F42: =IF(F41=0,NA(),E42+F41) | G42: =IF(G41=0,NA(),F42+G41) | H42: =IF(H41=0,NA(),G42+H41) | I42: =IF(I41=0,NA(),H42+I41) | J42: =IF(J41=0,NA(),I42+J41) | ... Y42: =IF(Y41=0,NA(),X42+Y41)
A43: COSTO REAL (AC)  | B43: ='Avance semanal'!K6 | C43: ='Avance semanal'!K7 | D43: ='Avance semanal'!K8 | E43: ='Avance semanal'!K9 | F43: ='Avance semanal'!K10 | G43: ='Avance semanal'!K11 | H43: ='Avance semanal'!K12 | I43: ='Avance semanal'!K13 | J43: ='Avance semanal'!K14 | K43: ='Avance semanal'!K15
A44: Costo Real acumulado | B44: =IF(B41=0,NA(),B43) | C44: =IF(C41=0,NA(),B44+C43) | D44: =IF(D41=0,NA(),C44+D43) | E44: =IF(E41=0,NA(),D44+E43) | F44: =IF(F41=0,NA(),E44+F43) | G44: =IF(G41=0,NA(),F44+G43) | H44: =IF(H41=0,NA(),G44+H43) | I44: =IF(I41=0,NA(),H44+I43) | J44: =IF(J41=0,NA(),I44+J43) | ... Y44: =IF(Y41=0,NA(),X44+Y43)
A45: SPI | B45: =IFERROR(B42/B40,"-") | C45: =IFERROR(C42/C40,"-") | D45: =IFERROR(D42/D40,"-") | E45: =IFERROR(E42/E40,"-") | F45: =IFERROR(F42/F40,"-") | G45: =IFERROR(G42/G40,"-") | H45: =IFERROR(H42/H40,"-") | I45: =IFERROR(I42/I40,"-") | ... Y45: =IFERROR(Y42/Y40,"-")
A46: CPI | B46: =IFERROR(B42/B44,"-") | C46: =IFERROR(C42/C44,"-") | D46: =IFERROR(D42/D44,"-") | E46: =IFERROR(E42/E44,"-") | F46: =IFERROR(F42/F44,"-") | G46: =IFERROR(G42/G44,"-") | H46: =IFERROR(H42/H44,"-") | I46: =IFERROR(I42/I44,"-") | ... Y46: =IFERROR(Y42/Y44,"-")

Sheet Curva S
A1: SportMatch — Valor Ganado (EVM) y Curva S
A2: Equipo 11 · Corte 15/10/2026 (semana 10, cierre del S2) · USD acumulados (devs + leads + infra + IA + 10 % de contingencia de actividades) · Base: WBS y Cronograma v4 · Datos desde PRESUPUESTO y Avance semanal
A4: Semana | B4: Cierre (jueves) | C4: Hito | D4: PV acumulado (USD) | E4: EV acumulado (USD) | F4: AC acumulado (USD) | G4: Horas plan acum. (devs) | H4: Horas ganadas acum. (WBS) | I4: Horas reales acum. (devs) | K4: Parámetros
A5: 1 | B5: 13/08 | C5: S1 · Capacitación | D5: =PRESUPUESTO!B40 | E5: =IFERROR(PRESUPUESTO!B42,"") | F5: =IFERROR(PRESUPUESTO!B44,"") | G5: =SUM('Avance semanal'!$D$6:D6) | H5: =SUM('Avance semanal'!$F$6:F6) | I5: =SUM('Avance semanal'!$E$6:E6) | K5: Semana de corte | L5: 10
A6: 2 | B6: 20/08 | C6: S1 | D6: =PRESUPUESTO!C40 | E6: =IFERROR(PRESUPUESTO!C42,"") | F6: =IFERROR(PRESUPUESTO!C44,"") | G6: =SUM('Avance semanal'!$D$6:D7) | H6: =SUM('Avance semanal'!$F$6:F7) | I6: =SUM('Avance semanal'!$E$6:E7) | K6: Tarifa desarrollo (USD/h) | L6: 10
A7: 3 | B7: 27/08 | C7: S1 | D7: =PRESUPUESTO!D40 | E7: =IFERROR(PRESUPUESTO!D42,"") | F7: =IFERROR(PRESUPUESTO!D44,"") | G7: =SUM('Avance semanal'!$D$6:D8) | H7: =SUM('Avance semanal'!$F$6:F8) | I7: =SUM('Avance semanal'!$E$6:E8) | K7: Contingencia de actividades (% del costo, dentro del BAC) | L7: 0.1
A8: 4 | B8: 03/09 | C8: S1 | D8: =PRESUPUESTO!E40 | E8: =IFERROR(PRESUPUESTO!E42,"") | F8: =IFERROR(PRESUPUESTO!E44,"") | G8: =SUM('Avance semanal'!$D$6:D9) | H8: =SUM('Avance semanal'!$F$6:F9) | I8: =SUM('Avance semanal'!$E$6:E9) | K8: BAC línea base EVM = BAC del proyecto (devs + leads + infra + IA + contingencia de actividades) | L8: =PRESUPUESTO!Z39
A9: 5 | B9: 10/09 | C9: S1 | D9: =PRESUPUESTO!F40 | E9: =IFERROR(PRESUPUESTO!F42,"") | F9: =IFERROR(PRESUPUESTO!F44,"") | G9: =SUM('Avance semanal'!$D$6:D10) | H9: =SUM('Avance semanal'!$F$6:F10) | I9: =SUM('Avance semanal'!$E$6:E10) | K9: Esfuerzo de desarrollo (h, Cronograma v4 con 13.1 a 6 h) | L9: 227.62
A10: 6 | B10: 17/09 | C10: S1 · Steering 1 | D10: =PRESUPUESTO!G40 | E10: =IFERROR(PRESUPUESTO!G42,"") | F10: =IFERROR(PRESUPUESTO!G44,"") | G10: =SUM('Avance semanal'!$D$6:D11) | H10: =SUM('Avance semanal'!$F$6:F11) | I10: =SUM('Avance semanal'!$E$6:E11) | K10: Métrica al corte | L10: USD | M10: Horas (devs) | N10: Lectura
A11: 7 | B11: 24/09 | C11: S2 | D11: =PRESUPUESTO!H40 | E11: =IFERROR(PRESUPUESTO!H42,"") | F11: =IFERROR(PRESUPUESTO!H44,"") | G11: =SUM('Avance semanal'!$D$6:D12) | H11: =SUM('Avance semanal'!$F$6:F12) | I11: =SUM('Avance semanal'!$E$6:E12) | K11: PV — Valor Planeado | L11: =INDEX(PRESUPUESTO!$B$40:$Y$40,$L$5) | M11: =INDEX($G$5:$G$17,$L$5)
A12: 8 | B12: 01/10 | C12: S2 | D12: =PRESUPUESTO!I40 | E12: =IFERROR(PRESUPUESTO!I42,"") | F12: =IFERROR(PRESUPUESTO!I44,"") | G12: =SUM('Avance semanal'!$D$6:D13) | H12: =SUM('Avance semanal'!$F$6:F13) | I12: =SUM('Avance semanal'!$E$6:E13) | K12: EV — Valor Ganado | L12: =INDEX(PRESUPUESTO!$B$42:$Y$42,$L$5) | M12: =INDEX($H$5:$H$17,$L$5)
A13: 9 | B13: 08/10 | C13: S2 | D13: =PRESUPUESTO!J40 | E13: =IFERROR(PRESUPUESTO!J42,"") | F13: =IFERROR(PRESUPUESTO!J44,"") | G13: =SUM('Avance semanal'!$D$6:D14) | H13: =SUM('Avance semanal'!$F$6:F14) | I13: =SUM('Avance semanal'!$E$6:E14) | K13: AC — Costo Real | L13: =INDEX(PRESUPUESTO!$B$44:$Y$44,$L$5) | M13: =INDEX($I$5:$I$17,$L$5)
A14: 10 | B14: 15/10 | C14: S2 · CORTE (steering 2) · MVP | D14: =PRESUPUESTO!K40 | E14: =IFERROR(PRESUPUESTO!K42,"") | F14: =IFERROR(PRESUPUESTO!K44,"") | G14: =SUM('Avance semanal'!$D$6:D15) | H14: =SUM('Avance semanal'!$F$6:F15) | I14: =SUM('Avance semanal'!$E$6:E15) | K14: CV = EV − AC | L14: =L12-L13 | M14: =M12-M13 | N14: =IF(L14>=0,"Bajo presupuesto","Sobre presupuesto")
A15: 11 | B15: 22/10 | C15: S3 | D15: =PRESUPUESTO!L40 | E15: =IFERROR(PRESUPUESTO!L42,"") | F15: =IFERROR(PRESUPUESTO!L44,"") | G15: =SUM('Avance semanal'!$D$6:D16) | K15: SV = EV − PV | L15: =L12-L11 | M15: =M12-M11 | N15: =IF(L15>=0,"Adelantado al plan","Atrasado")
A16: 12 | B16: 29/10 | C16: S3 | D16: =PRESUPUESTO!M40 | E16: =IFERROR(PRESUPUESTO!M42,"") | F16: =IFERROR(PRESUPUESTO!M44,"") | G16: =SUM('Avance semanal'!$D$6:D17) | K16: CPI = EV / AC | L16: =L12/L13 | N16: =IF(L16>=1,"Eficiente en costo (>1)","Ineficiente (<1)")
A17: 13 | B17: 05/11 | C17: S3 · Fin del desarrollo | D17: =PRESUPUESTO!N40 | E17: =IFERROR(PRESUPUESTO!N42,"") | F17: =IFERROR(PRESUPUESTO!N44,"") | G17: =SUM('Avance semanal'!$D$6:D18) | K17: SPI = EV / PV | L17: =L12/L11 | N17: =IF(L17>=1,"Por encima del ritmo (>1)","Por debajo del ritmo (<1)")
A18: Gráfico: Curva S — PV vs EV vs AC | K18: EAC = BAC EVM / CPI | L18: =L8/L16 | N18: Costo estimado al cierre
K19: ETC = EAC − AC | L19: =L18-L13 | N19: Costo para completar
K20: VAC = BAC EVM − EAC | L20: =L8-L18 | N20: =IF(L20>=0,"Ahorro proyectado","Sobrecosto proyectado")
K21: BAC desarrollo (devs + infra + IA) | L21: =SUM(PRESUPUESTO!Z9:Z14)
K22: Tarifa leads (USD/h) | L22: 20
K23: Notas y supuestos
K24: • PV: 3 devs (6 h/sem × 10 USD/h = 60 USD/sem c/u) + 4 leads (PM, PO, Tech Lead y QA Lead: 4 h/sem × 20 USD/h = 80 USD/sem c/u) durante 13 semanas + Azure B1 desde el deploy (29/08) + Claude Code/ChatGPT (3 × 20 USD/mes). No entran la reserva de gestión (contingencia de gestión, 10 % = 671,94 USD) ni la semana de reserva (05/11 → 12/11).
K25: • Vercel (Hobby), Neon (Free), Google Maps y Google Places no tienen costo. Firebase Auth, GitHub Actions y GHCR tampoco.
K26: • EV = (EV desarrollo + EV leads) × (1 + contingencia de actividades). EV desarrollo = % completo × BAC desarrollo (L21); % completo = horas estimadas de los paquetes de la WBS cerrados / 227,62 h. Semanal: 5,5 · 32,71 · 8,72 · 30,3 · 26,29 · 20,18 · 7,83 · 21,14 · 24,42 · 16,22 h (193,31 h).
K27: • Leads como level of effort: su trabajo no se cierra por paquetes, así que EV = PV. AC: 18 h reales/sem de devs + 16 h reales/sem de leads (22 h en la semana 9 por el challenge) + lo facturado de infra e IA. El detalle está en la hoja Avance semanal.
K28: • Contingencia en el EVM (cambio respecto del Steering 1): la contingencia de actividades (10 %) es parte de la línea base de costos (PMBOK 7.3), así que se reparte en proporción al trabajo planificado (fila 19 de PRESUPUESTO) y PV y EV van × 1,1. El BAC del EVM (L8) es el BAC del proyecto: 6.719,42 + 10 % = 7.391,36 USD, sin CAPEX. La contingencia de gestión (otro 10 %, 671,94 USD) es reserva de gestión: queda fuera del BAC y del EVM. Presupuesto total: 8.063,30 USD. El AC es el gasto real, también el que cubre la contingencia. El CPI incluye la contingencia no usada: sin ella da 1,01.
K29: • Cambio respecto del Steering 1: la curva incluye a los leads (incidente Sem08 del tablero: se había omitido su valor). Las semanas 1 a 6 se recalcularon con la base nueva.
K30: • Los N/A de PRESUPUESTO (semanas 11 a 24) vienen de la plantilla y cortan las curvas EV y AC en la semana de corte.
K31: • En el gráfico, EV y AC toman PRESUPUESTO!B:K (semanas 1 a 10). Al cargar semanas nuevas, extender el rango de esas dos series.
K32: • Celdas amarillas con texto azul = datos a editar. Texto verde = vínculo a otra hoja.
K33: • Divisor de 227,62 h: las 225,62 h del Cronograma v4 (78 paquetes, con la épica 13.0 sumada el 07/10) con 13.1 re-estimada de 4 h a 6 h (Lab2: SPO-276 y SPO-277, ADR-001). Lab4 (workflow, alertas y ADR, 6 h) lo hicieron los leads por encima de su level of effort: suma 6 h × 20 USD = 120 USD al AC de la semana 9 y se cubre con la contingencia de actividades (671,94 → 551,94 USD). El EV no cambia porque Lab4 no está en la línea base.
K34: • Semana 10: SPO-262, SPO-264 y SPO-279 cerraron en Linear el 13/10 y el 14/10. Lo que está en Backlog no suma: 6.5.1 queda pendiente por SPO-259.
... K36: • Roles de los leads. S1: PM Chialva, PO Valle, Tech Lead Bogo, QA Chevallier. Desde la semana 7: PM Chevallier, PO Chialva, Tech Lead Valle, QA Bogo.

Sheet Avance semanal
A1: SportMatch — Avance semanal (horas y valor ganado)
A2: Equipo 11 · Semanas de jueves a jueves (06/08 → 05/11) · S1 = sem 1–6, S2 = 7–10, S3 = 11–13 · Corte 15/10 (semana 10) · Reserva 05/11 → 12/11 fuera del BAC · Celdas amarillas = datos a editar
A5: Semana | B5: Cierre | C5: Hito | D5: Horas plan (devs) | E5: Horas reales (devs) | F5: Horas ganadas (WBS) | G5: % completo de la semana | H5: Infra + IA plan (USD) | I5: Infra + IA real (USD) | J5: EV total (USD) = (% × BAC desarrollo + leads) × (1 + contingencia de actividades) | K5: AC total (USD) | L5: Horas leads plan | M5: Horas leads reales | N5: Qué pasó en la semana
A6: 1 | B6: 13/08 | C6: S1 · Capacitación | D6: =(PRESUPUESTO!B9+PRESUPUESTO!B10+PRESUPUESTO!B11)/'Curva S'!$L$6 | E6: 18 | F6: 5.5 | G6: =F6/'Curva S'!$L$9 | H6: =PRESUPUESTO!B12+PRESUPUESTO!B13+PRESUPUESTO!B14 | I6: =H6 | J6: =(G6*'Curva S'!$L$21+L6*'Curva S'!$L$22)*(1+'Curva S'!$L$7) | K6: =E6*'Curva S'!$L$6+I6+M6*'Curva S'!$L$22 | L6: =(PRESUPUESTO!B15+PRESUPUESTO!B16+PRESUPUESTO!B17+PRESUPUESTO!B18)/'Curva S'!$L$22 | M6: 16 | N6: Cierran 3.1.1, 3.1.3
A7: 2 | B7: 20/08 | C7: S1 | D7: =(PRESUPUESTO!C9+PRESUPUESTO!C10+PRESUPUESTO!C11)/'Curva S'!$L$6 | E7: 18 | F7: 32.71 | G7: =F7/'Curva S'!$L$9 | H7: =PRESUPUESTO!C12+PRESUPUESTO!C13+PRESUPUESTO!C14 | I7: =H7 | J7: =(G7*'Curva S'!$L$21+L7*'Curva S'!$L$22)*(1+'Curva S'!$L$7) | K7: =E7*'Curva S'!$L$6+I7+M7*'Curva S'!$L$22 | L7: =(PRESUPUESTO!C15+PRESUPUESTO!C16+PRESUPUESTO!C17+PRESUPUESTO!C18)/'Curva S'!$L$22 | M7: 16 | N7: Cierran 3.1.2, 3.2.1, 4.1.1, 4.1.3, 4.1.4, 4.2.1, 4.2.2, 4.2.3, 10.2.1
A8: 3 | B8: 27/08 | C8: S1 | D8: =(PRESUPUESTO!D9+PRESUPUESTO!D10+PRESUPUESTO!D11)/'Curva S'!$L$6 | E8: 18 | F8: 8.72 | G8: =F8/'Curva S'!$L$9 | H8: =PRESUPUESTO!D12+PRESUPUESTO!D13+PRESUPUESTO!D14 | I8: =H8 | J8: =(G8*'Curva S'!$L$21+L8*'Curva S'!$L$22)*(1+'Curva S'!$L$7) | K8: =E8*'Curva S'!$L$6+I8+M8*'Curva S'!$L$22 | L8: =(PRESUPUESTO!D15+PRESUPUESTO!D16+PRESUPUESTO!D17+PRESUPUESTO!D18)/'Curva S'!$L$22 | M8: 16 | N8: Cierran 3.2.2, 4.1.2, 6.1.1, 9.1.4
A9: 4 | B9: 03/09 | C9: S1 | D9: =(PRESUPUESTO!E9+PRESUPUESTO!E10+PRESUPUESTO!E11)/'Curva S'!$L$6 | E9: 18 | F9: 30.3 | G9: =F9/'Curva S'!$L$9 | H9: =PRESUPUESTO!E12+PRESUPUESTO!E13+PRESUPUESTO!E14 | I9: =H9 | J9: =(G9*'Curva S'!$L$21+L9*'Curva S'!$L$22)*(1+'Curva S'!$L$7) | K9: =E9*'Curva S'!$L$6+I9+M9*'Curva S'!$L$22 | L9: =(PRESUPUESTO!E15+PRESUPUESTO!E16+PRESUPUESTO!E17+PRESUPUESTO!E18)/'Curva S'!$L$22 | M9: 16 | N9: Cierran 3.2.3, 4.2.5, 6.1.2, 6.1.5, 6.2.3, 6.3.5, 7.2.1, 9.1.1, 9.1.2, 9.1.3
A10: 5 | B10: 10/09 | C10: S1 | D10: =(PRESUPUESTO!F9+PRESUPUESTO!F10+PRESUPUESTO!F11)/'Curva S'!$L$6 | E10: 18 | F10: 26.29 | G10: =F10/'Curva S'!$L$9 | H10: =PRESUPUESTO!F12+PRESUPUESTO!F13+PRESUPUESTO!F14 | I10: =H10 | J10: =(G10*'Curva S'!$L$21+L10*'Curva S'!$L$22)*(1+'Curva S'!$L$7) | K10: =E10*'Curva S'!$L$6+I10+M10*'Curva S'!$L$22 | L10: =(PRESUPUESTO!F15+PRESUPUESTO!F16+PRESUPUESTO!F17+PRESUPUESTO!F18)/'Curva S'!$L$22 | M10: 16 | N10: Cierran 5.1.2, 5.2.1, 6.1.3, 6.2.1, 6.2.4, 6.3.1, 6.3.2, 6.3.3, 7.2.2
A11: 6 | B11: 17/09 | C11: S1 · Steering 1 | D11: =(PRESUPUESTO!G9+PRESUPUESTO!G10+PRESUPUESTO!G11)/'Curva S'!$L$6 | E11: 18 | F11: 20.18 | G11: =F11/'Curva S'!$L$9 | H11: =PRESUPUESTO!G12+PRESUPUESTO!G13+PRESUPUESTO!G14 | I11: =H11 | J11: =(G11*'Curva S'!$L$21+L11*'Curva S'!$L$22)*(1+'Curva S'!$L$7) | K11: =E11*'Curva S'!$L$6+I11+M11*'Curva S'!$L$22 | L11: =(PRESUPUESTO!G15+PRESUPUESTO!G16+PRESUPUESTO!G17+PRESUPUESTO!G18)/'Curva S'!$L$22 | M11: 16 | N11: Cierran 4.2.4, 5.1.3, 5.1.5, 5.2.4, 5.2.5, 6.2.2, 6.3.4, 6.4.1, 6.4.2
A12: 7 | B12: 24/09 | C12: S2 | D12: =(PRESUPUESTO!H9+PRESUPUESTO!H10+PRESUPUESTO!H11)/'Curva S'!$L$6 | E12: 18 | F12: 7.83 | G12: =F12/'Curva S'!$L$9 | H12: =PRESUPUESTO!H12+PRESUPUESTO!H13+PRESUPUESTO!H14 | I12: =H12 | J12: =(G12*'Curva S'!$L$21+L12*'Curva S'!$L$22)*(1+'Curva S'!$L$7) | K12: =E12*'Curva S'!$L$6+I12+M12*'Curva S'!$L$22 | L12: =(PRESUPUESTO!H15+PRESUPUESTO!H16+PRESUPUESTO!H17+PRESUPUESTO!H18)/'Curva S'!$L$22 | M12: 16 | N12: Cierran 5.2.3, 6.1.4, 6.2.5, 11.1.1
A13: 8 | B13: 01/10 | C13: S2 | D13: =(PRESUPUESTO!I9+PRESUPUESTO!I10+PRESUPUESTO!I11)/'Curva S'!$L$6 | E13: 18 | F13: 21.14 | G13: =F13/'Curva S'!$L$9 | H13: =PRESUPUESTO!I12+PRESUPUESTO!I13+PRESUPUESTO!I14 | I13: =H13 | J13: =(G13*'Curva S'!$L$21+L13*'Curva S'!$L$22)*(1+'Curva S'!$L$7) | K13: =E13*'Curva S'!$L$6+I13+M13*'Curva S'!$L$22 | L13: =(PRESUPUESTO!I15+PRESUPUESTO!I16+PRESUPUESTO!I17+PRESUPUESTO!I18)/'Curva S'!$L$22 | M13: 16 | N13: Cierran 6.2.6, 7.1.1, 7.3.2, 7.3.3, 11.1.3, 11.2.1
A14: 9 | B14: 08/10 | C14: S2 | D14: =(PRESUPUESTO!J9+PRESUPUESTO!J10+PRESUPUESTO!J11)/'Curva S'!$L$6 | E14: 18 | F14: 24.42 | G14: =F14/'Curva S'!$L$9 | H14: =PRESUPUESTO!J12+PRESUPUESTO!J13+PRESUPUESTO!J14 | I14: =H14 | J14: =(G14*'Curva S'!$L$21+L14*'Curva S'!$L$22)*(1+'Curva S'!$L$7) | K14: =E14*'Curva S'!$L$6+I14+M14*'Curva S'!$L$22 | L14: =(PRESUPUESTO!J15+PRESUPUESTO!J16+PRESUPUESTO!J17+PRESUPUESTO!J18)/'Curva S'!$L$22 | M14: 22 | N14: Cierran 5.1.1, 5.1.4, 6.4.3, 7.1.3, 7.3.1, 11.1.2, 11.2.2, 13.1.1, 13.1.2 (challenge, 13.1 re-estimada a 6 h) · Leads: +6 h de Lab4 (workflow, alertas y ADR), de la contingencia
A15: 10 | B15: 15/10 | C15: S2 · CORTE (steering 2) · MVP | D15: =(PRESUPUESTO!K9+PRESUPUESTO!K10+PRESUPUESTO!K11)/'Curva S'!$L$6 | E15: 18 | F15: 16.22 | G15: =F15/'Curva S'!$L$9 | H15: =PRESUPUESTO!K12+PRESUPUESTO!K13+PRESUPUESTO!K14 | I15: =H15 | J15: =(G15*'Curva S'!$L$21+L15*'Curva S'!$L$22)*(1+'Curva S'!$L$7) | K15: =E15*'Curva S'!$L$6+I15+M15*'Curva S'!$L$22 | L15: =(PRESUPUESTO!K15+PRESUPUESTO!K16+PRESUPUESTO!K17+PRESUPUESTO!K18)/'Curva S'!$L$22 | M15: 16 | N15: Cierran 5.2.2, 6.5.2, 6.5.3, 7.1.2, 12.1.1, 12.1.2 (5.2.2 y 6.5.3 cerraron el 13/10 y el 14/10)
A16: 11 | B16: 22/10 | C16: S3 | D16: =(PRESUPUESTO!L9+PRESUPUESTO!L10+PRESUPUESTO!L11)/'Curva S'!$L$6 | H16: =PRESUPUESTO!L12+PRESUPUESTO!L13+PRESUPUESTO!L14 | L16: =(PRESUPUESTO!L15+PRESUPUESTO!L16+PRESUPUESTO!L17+PRESUPUESTO!L18)/'Curva S'!$L$22 | N16: Pendiente (línea base)
A17: 12 | B17: 29/10 | C17: S3 | D17: =(PRESUPUESTO!M9+PRESUPUESTO!M10+PRESUPUESTO!M11)/'Curva S'!$L$6 | H17: =PRESUPUESTO!M12+PRESUPUESTO!M13+PRESUPUESTO!M14 | L17: =(PRESUPUESTO!M15+PRESUPUESTO!M16+PRESUPUESTO!M17+PRESUPUESTO!M18)/'Curva S'!$L$22 | N17: Pendiente (línea base)
A18: 13 | B18: 05/11 | C18: S3 · Fin del desarrollo | D18: =(PRESUPUESTO!N9+PRESUPUESTO!N10+PRESUPUESTO!N11)/'Curva S'!$L$6 | H18: =PRESUPUESTO!N12+PRESUPUESTO!N13+PRESUPUESTO!N14 | L18: =(PRESUPUESTO!N15+PRESUPUESTO!N16+PRESUPUESTO!N17+PRESUPUESTO!N18)/'Curva S'!$L$22 | N18: Pendiente (línea base)
A19: Total al corte | D19: =SUM(D6:D15) | E19: =SUM(E6:E15) | F19: =SUM(F6:F15) | G19: =SUM(G6:G15) | H19: =SUM(H6:H15) | I19: =SUM(I6:I15) | J19: =SUM(J6:J15) | K19: =SUM(K6:K15) | ... M19: =SUM(M6:M15) | N19: Semanas 1 a 10
A20: Cómo leer esta hoja
A21: • Horas plan y reales (devs): 3 devs × 6 h/sem, de las filas de devs de PRESUPUESTO; reales 18 h/sem. Horas leads: 4 leads × 4 h/sem, de las filas 15 a 18 de PRESUPUESTO; reales 16 h/sem (22 h en la semana 9: +6 h de Lab4 por el challenge, cubiertas con la contingencia).
A22: • Horas ganadas: horas estimadas (WBS v4) de los paquetes que cierran en la semana, con la fecha de cierre de Linear (sync del 12/10). Total al corte: 193,31 h de 227,62 h de desarrollo (84,9 %). Los paquetes parciales no suman; los arreglos sobre paquetes ya cerrados tampoco.
A23: • Infra + IA: Azure B1 (13,14 USD/mes) desde el deploy del 29/08 (SPO-175/176) y Claude Code/ChatGPT (3 × 20 USD/mes, se cobra el 10 de cada mes). Semanas 7 a 10: lo facturado coincide con el plan (confirmado el 14/10).
A24: • EV total = (% completo × BAC desarrollo (Curva S!L21) + horas leads plan × tarifa leads) × (1 + contingencia de actividades, Curva S!L7). Leads como level of effort: EV = PV. AC total = horas reales devs × tarifa dev + horas reales leads × tarifa leads + Infra/IA facturados (sin contingencia: es gasto real). Ambas columnas alimentan las filas 41 y 43 de PRESUPUESTO.
A25: • Semana 10: SPO-262, SPO-264 y SPO-279 cerraron en Linear el 13/10 y el 14/10. Lo que está en Backlog no suma.

Sheet Ayuda
